README.txt
setup.py
pageinfo/__init__.py
pageinfo/pageinfo.py
pageinfo.egg-info/PKG-INFO
pageinfo.egg-info/SOURCES.txt
pageinfo.egg-info/dependency_links.txt
pageinfo.egg-info/not-zip-safe
pageinfo.egg-info/requires.txt
pageinfo.egg-info/top_level.txt