Metadata-Version: 1.0
Name: pageinfo
Version: 0.2
Summary: Tool for extracting basic information from web pages
Home-page: https://github.com/nytlabs/pageinfo
Author: Alexis Lloyd
Author-email: alexislloyd@gmail.com
License: Apache
Keywords: metadata title web page url description twitter facebook
Platform: UNKNOWN
